examplebtuFibonacciMariam/__init__.py
examplebtuFibonacciMariam/example.py
examplebtuFibonacciMariam-0.0.1.dist-info/LICENSE.txt
examplebtuFibonacciMariam-0.0.1.dist-info/METADATA
examplebtuFibonacciMariam-0.0.1.dist-info/WHEEL
examplebtuFibonacciMariam-0.0.1.dist-info/top_level.txt
examplebtuFibonacciMariam-0.0.1.dist-info/RECORD
