Metadata-Version: 2.1
Name: examplebtuFibonacciMariam
Version: 0.0.1
Summary: Test Project
Author: mariamaludauri1
Author-email: aludaurim@gmail.com
Classifier: Programming Language :: Python :: 3
Classifier: License :: OSI Approved :: MIT License
Classifier: Operating System :: OS Independent
Requires-Python: >=3.6
License-File: LICENSE.txt
